Metadata-Version: 1.0
Name: c-salt
Version: 1.0.0
Summary: Sales and Leads prediction for Franchise dealers
Home-page: https://git.corp.tc/lgolod/C_SALT/tree/master/packages/c_salt
Author: Lev Golod
Author-email: lgolod@truecar.com
License: Proprietary
Platform: UNKNOWN
